ws2g/__init__.py
ws2g/custom_content_parser/__init__.py
ws2g/custom_content_parser/custom_content_parser.py
ws2g/main.py
ws2g/repository/__init__.py
ws2g/repository/repository.py
ws2g/repository/sqlrepository.py
ws2g/views/__init__.py
ws2g/views/views.py
ws2g-0.1.0.dist-info/LICENSE
ws2g-0.1.0.dist-info/METADATA
ws2g-0.1.0.dist-info/WHEEL
ws2g-0.1.0.dist-info/RECORD
