Metadata-Version: 2.1
Name: ws2g
Version: 0.1.0
Summary: A webserver to use when you have no time for configuration
Home-page: https://github.com/arazi47/built-to-serve
License: MIT
Author: Alexis Razi
Author-email: razialexis43@gmail.com
Requires-Python: >=3.11,<4.0
Classifier: License :: OSI Approved :: MIT License
Classifier: Programming Language :: Python :: 3
Classifier: Programming Language :: Python :: 3.11
Requires-Dist: black (>=23.7.0,<24.0.0)
Requires-Dist: pymongo (>=4.5.0,<5.0.0)
Requires-Dist: pytest (>=7.4.1,<8.0.0)
Requires-Dist: pytest-cov (>=4.1.0,<5.0.0)
Requires-Dist: ruff (>=0.0.287,<0.0.288)
Project-URL: Bug Tracker, https://github.com/arazi47/built-to-serve/issues
Project-URL: Repository, https://github.com/arazi47/built-to-serve
